README.md
setup.py
dj_streamio.egg-info/PKG-INFO
dj_streamio.egg-info/SOURCES.txt
dj_streamio.egg-info/dependency_links.txt
dj_streamio.egg-info/requires.txt
dj_streamio.egg-info/top_level.txt
streamio/__init__.py
streamio/admin.py
streamio/apps.py
streamio/helpers.py
streamio/mixins.py
streamio/models.py
streamio/snippets.py
streamio/streamio.py
streamio/tests.py
streamio/views.py
streamio/viewsets.py
streamio/viewsets_legacy.py